reearthcmsapi/__init__.py
reearthcmsapi/api_client.py
reearthcmsapi/configuration.py
reearthcmsapi/exceptions.py
reearthcmsapi/rest.py
reearthcmsapi/schemas.py
reearthcmsapi/apis/__init__.py
reearthcmsapi/apis/path_to_api.py
reearthcmsapi/apis/tag_to_api.py
reearthcmsapi/apis/paths/__init__.py
reearthcmsapi/apis/paths/assets_asset_id.py
reearthcmsapi/apis/paths/assets_asset_id_comments.py
reearthcmsapi/apis/paths/assets_asset_id_comments_comment_id.py
reearthcmsapi/apis/paths/items_item_id.py
reearthcmsapi/apis/paths/items_item_id_comments.py
reearthcmsapi/apis/paths/items_item_id_comments_comment_id.py
reearthcmsapi/apis/paths/models_model_id.py
reearthcmsapi/apis/paths/models_model_id_items.py
reearthcmsapi/apis/paths/projects_project_id_assets.py
reearthcmsapi/apis/paths/projects_project_id_or_alias_models_model_id_or_key.py
reearthcmsapi/apis/paths/projects_project_id_or_alias_models_model_id_or_key_items.py
reearthcmsapi/apis/tags/__init__.py
reearthcmsapi/apis/tags/assets_api.py
reearthcmsapi/apis/tags/assets_comments_api.py
reearthcmsapi/apis/tags/assets_project_api.py
reearthcmsapi/apis/tags/items_api.py
reearthcmsapi/apis/tags/items_comments_api.py
reearthcmsapi/apis/tags/items_project_api.py
reearthcmsapi/apis/tags/models_api.py
reearthcmsapi/model/__init__.py
reearthcmsapi/model/asset.py
reearthcmsapi/model/asset_embedding.py
reearthcmsapi/model/comment.py
reearthcmsapi/model/field.py
reearthcmsapi/model/file.py
reearthcmsapi/model/item.py
reearthcmsapi/model/model.py
reearthcmsapi/model/ref_or_version.py
reearthcmsapi/model/schema.py
reearthcmsapi/model/schema_field.py
reearthcmsapi/model/value_type.py
reearthcmsapi/model/version.py
reearthcmsapi/model/versioned_item.py
reearthcmsapi/models/__init__.py
reearthcmsapi/paths/__init__.py
reearthcmsapi/paths/assets_asset_id/__init__.py
reearthcmsapi/paths/assets_asset_id/delete.py
reearthcmsapi/paths/assets_asset_id/get.py
reearthcmsapi/paths/assets_asset_id_comments/__init__.py
reearthcmsapi-0.0.3.dist-info/LICENSE
reearthcmsapi-0.0.3.dist-info/METADATA
reearthcmsapi-0.0.3.dist-info/WHEEL
reearthcmsapi-0.0.3.dist-info/top_level.txt
reearthcmsapi-0.0.3.dist-info/RECORD
