Metadata-Version: 2.1
Name: reearthcmsapi
Version: 0.0.3
Summary: ReEarth-CMS Integration API
Home-page: https://github.com/reearth/reearth-cms-api
Author: Eukarya Inc.
License: MIT
Keywords: OpenAPI,OpenAPI-Generator,ReEarth-CMS Integration API
Requires-Python: >=3.7
License-File: LICENSE
Requires-Dist: certifi >=14.5.14
Requires-Dist: frozendict >=2.3.4
Requires-Dist: python-dateutil >=2.7.0
Requires-Dist: setuptools >=21.0.0
Requires-Dist: typing-extensions >=4.3.0
Requires-Dist: urllib3 <2.1.0,>=1.26.7
